orm_alchemy/__init__.py
orm_alchemy/alchemy.py
orm_alchemy/decorator.py
pilock-0.1.1.dist-info/LICENSE
pilock-0.1.1.dist-info/METADATA
pilock-0.1.1.dist-info/WHEEL
pilock-0.1.1.dist-info/RECORD
